{"2015":{"batters":{},"bullpen":{},"starters":{}},"2016":{"batters":{},"bullpen":{},"starters":{}},"2017":{"batters":{"aaron judge":"pages_y2017/NYY-batters-aaron-judge-aaron_judge.html"},"bullpen":{},"starters":{}},"2018":{"batters":{},"bullpen":{},"starters":{}},"2019":{"batters":{},"bullpen":{},"starters":{}},"2020":{"batters":{},"bullpen":{},"starters":{}},"2021":{"batters":{},"bullpen":{},"starters":{}},"2022":{"batters":{},"bullpen":{},"starters":{}},"2023":{"batters":{},"bullpen":{},"starters":{}},"2024":{"batters":{"aaron judge":"pages_y2024/NYY-batters-aaron-judge-aaron_judge.html"},"bullpen":{},"starters":{"tarik skubal":"pages_y2024/DET-starters-tarik-skubal-tarik_skubal.html"}},"2025":{"batters":{"aaron judge":"pages_y2025/NYY-batters-aaron-judge-aaron_judge.html"},"bullpen":{"luis garcia rp":"pages_y2025/RP-bullpen-luis-garcia-rp-luis_garcia_rp.html"},"starters":{"tarik skubal":"pages_y2025/DET-starters-tarik-skubal-tarik_skubal.html"}},"2026":{"batters":{},"bullpen":{},"starters":{}}}
